{
  "source": "臺灣銀行牌告匯率",
  "updateTime": "2026/07/21 09:07:00",
  "quoteTimeSource": "bot-page",
  "generatedAt": "2026-07-21T01:09:37.009Z",
  "details": {
    "USD": {
      "cash": {
        "buy": 31.89,
        "sell": 32.34
      },
      "spot": {
        "buy": 32.24,
        "sell": 32.327
      }
    },
    "HKD": {
      "cash": {
        "buy": 3.962,
        "sell": 4.148
      },
      "spot": {
        "buy": 4.088,
        "sell": 4.147
      }
    },
    "GBP": {
      "cash": {
        "buy": 42.18,
        "sell": 43.59
      },
      "spot": {
        "buy": 43.19,
        "sell": 43.568
      }
    },
    "AUD": {
      "cash": {
        "buy": 22.22,
        "sell": 22.71
      },
      "spot": {
        "buy": 22.51,
        "sell": 22.694
      }
    },
    "CAD": {
      "cash": {
        "buy": 22.45,
        "sell": 23.05
      },
      "spot": {
        "buy": 22.85,
        "sell": 23.049
      }
    },
    "SGD": {
      "cash": {
        "buy": 24.44,
        "sell": 25.11
      },
      "spot": {
        "buy": 24.93,
        "sell": 25.117
      }
    },
    "CHF": {
      "cash": {
        "buy": 39.03,
        "sell": 39.96
      },
      "spot": {
        "buy": 39.71,
        "sell": 39.987
      }
    },
    "JPY": {
      "cash": {
        "buy": 0.1894,
        "sell": 0.2007
      },
      "spot": {
        "buy": 0.1967,
        "sell": 0.2008
      }
    },
    "ZAR": {
      "cash": {
        "buy": 0,
        "sell": 1.995
      },
      "spot": {
        "buy": 1.915,
        "sell": 1.992
      }
    },
    "SEK": {
      "cash": {
        "buy": 0,
        "sell": 3.39
      },
      "spot": {
        "buy": 3.29,
        "sell": 3.39
      }
    },
    "NZD": {
      "cash": {
        "buy": 18.46,
        "sell": 19.04
      },
      "spot": {
        "buy": 18.84,
        "sell": 19.039
      }
    },
    "THB": {
      "cash": {
        "buy": 0.831,
        "sell": 0.9844
      },
      "spot": {
        "buy": 0.9444,
        "sell": 0
      }
    },
    "PHP": {
      "cash": {
        "buy": 0.4576,
        "sell": 0
      },
      "spot": {
        "buy": 0,
        "sell": 0
      }
    },
    "IDR": {
      "cash": {
        "buy": 0.00143,
        "sell": 0
      },
      "spot": {
        "buy": 0,
        "sell": 0
      }
    },
    "EUR": {
      "cash": {
        "buy": 36.04,
        "sell": 37.06
      },
      "spot": {
        "buy": 36.66,
        "sell": 37.056
      }
    },
    "KRW": {
      "cash": {
        "buy": 0.0201,
        "sell": 0
      },
      "spot": {
        "buy": 0,
        "sell": 0
      }
    },
    "VND": {
      "cash": {
        "buy": 0.00101,
        "sell": 0
      },
      "spot": {
        "buy": 0,
        "sell": 0
      }
    },
    "MYR": {
      "cash": {
        "buy": 6.871,
        "sell": 0
      },
      "spot": {
        "buy": 0,
        "sell": 0
      }
    },
    "CNY": {
      "cash": {
        "buy": 4.674,
        "sell": 4.796
      },
      "spot": {
        "buy": 4.746,
        "sell": 4.7966
      }
    }
  },
  "rates": {
    "USD": 1,
    "TWD": 32.283500000000004,
    "HKD": 7.840558591378265,
    "GBP": 0.7442195532400472,
    "AUD": 1.4283470489337229,
    "CAD": 1.406719100634001,
    "SGD": 1.2901272803564652,
    "CHF": 0.8101559657201652,
    "JPY": 162.43270440251572,
    "ZAR": 16.52597901202969,
    "SEK": 9.665718562874252,
    "NZD": 1.704559254468175,
    "THB": 68.36827615417197,
    "EUR": 0.8758885452276305,
    "CNY": 6.766185316370801
  }
}