{
  "source": "臺灣銀行牌告匯率",
  "updateTime": "2026/07/21 19:22:00",
  "quoteTimeSource": "bot-page",
  "generatedAt": "2026-07-21T11:39:01.161Z",
  "details": {
    "USD": {
      "cash": {
        "buy": 31.97,
        "sell": 32.445
      },
      "spot": {
        "buy": 32.295,
        "sell": 32.418
      }
    },
    "HKD": {
      "cash": {
        "buy": 3.972,
        "sell": 4.163
      },
      "spot": {
        "buy": 4.093,
        "sell": 4.158
      }
    },
    "GBP": {
      "cash": {
        "buy": 42.22,
        "sell": 43.745
      },
      "spot": {
        "buy": 43.115,
        "sell": 43.718
      }
    },
    "AUD": {
      "cash": {
        "buy": 22.33,
        "sell": 22.89
      },
      "spot": {
        "buy": 22.545,
        "sell": 22.804
      }
    },
    "CAD": {
      "cash": {
        "buy": 22.53,
        "sell": 23.19
      },
      "spot": {
        "buy": 22.86,
        "sell": 23.129
      }
    },
    "SGD": {
      "cash": {
        "buy": 24.52,
        "sell": 25.21
      },
      "spot": {
        "buy": 24.99,
        "sell": 25.207
      }
    },
    "CHF": {
      "cash": {
        "buy": 39.13,
        "sell": 40.13
      },
      "spot": {
        "buy": 39.74,
        "sell": 40.127
      }
    },
    "JPY": {
      "cash": {
        "buy": 0.1898,
        "sell": 0.2016
      },
      "spot": {
        "buy": 0.1966,
        "sell": 0.2013
      }
    },
    "ZAR": {
      "cash": {
        "buy": 0,
        "sell": 2.014
      },
      "spot": {
        "buy": 1.924,
        "sell": 2.007
      }
    },
    "SEK": {
      "cash": {
        "buy": 0,
        "sell": 3.41
      },
      "spot": {
        "buy": 3.29,
        "sell": 3.41
      }
    },
    "NZD": {
      "cash": {
        "buy": 18.46,
        "sell": 19.09
      },
      "spot": {
        "buy": 18.79,
        "sell": 19.079
      }
    },
    "THB": {
      "cash": {
        "buy": 0.8335,
        "sell": 0.9899
      },
      "spot": {
        "buy": 0.9439,
        "sell": 0
      }
    },
    "PHP": {
      "cash": {
        "buy": 0.4582,
        "sell": 0
      },
      "spot": {
        "buy": 0,
        "sell": 0
      }
    },
    "IDR": {
      "cash": {
        "buy": 0.00148,
        "sell": 0
      },
      "spot": {
        "buy": 0,
        "sell": 0
      }
    },
    "EUR": {
      "cash": {
        "buy": 36.18,
        "sell": 37.295
      },
      "spot": {
        "buy": 36.695,
        "sell": 37.189
      }
    },
    "KRW": {
      "cash": {
        "buy": 0.02017,
        "sell": 0
      },
      "spot": {
        "buy": 0,
        "sell": 0
      }
    },
    "VND": {
      "cash": {
        "buy": 0.00098,
        "sell": 0
      },
      "spot": {
        "buy": 0,
        "sell": 0
      }
    },
    "MYR": {
      "cash": {
        "buy": 6.89,
        "sell": 0
      },
      "spot": {
        "buy": 0,
        "sell": 0
      }
    },
    "CNY": {
      "cash": {
        "buy": 4.688,
        "sell": 4.815
      },
      "spot": {
        "buy": 4.755,
        "sell": 4.8109
      }
    }
  },
  "rates": {
    "USD": 1,
    "TWD": 32.3565,
    "HKD": 7.843049327354258,
    "GBP": 0.7452581391867147,
    "AUD": 1.4269994928223333,
    "CAD": 1.4071408380264843,
    "SGD": 1.2891806283244016,
    "CHF": 0.8102595565127022,
    "JPY": 162.63634078914296,
    "ZAR": 16.46222335283643,
    "SEK": 9.658656716417909,
    "NZD": 1.7088647706567375,
    "THB": 68.5591694035385,
    "EUR": 0.8758729900925775,
    "CNY": 6.764967227338777
  }
}